{
  "openingCalls": [
    { "level": "Basic", "call": "Flutter Wheel|Sweep 1/4" },
    { "level": "Basic", "call": "Slide Thru|Double Pass Thru" },
    { "level": "Basic", "call": "Right and Left Thru|Rollaway|Star Thru" },
    { "level": "Basic", "call": "Pass the Ocean|GIRLS Trade|Recycle|Pass Thru" },
    { "level": "Basic", "call": "Turn Thru|Separate around 2 to a Line" },
    { "level": "Basic", "call": "Join Hands|Circle Left 3/4" },
    { "level": "Basic", "call": "Touch 1/4|Walk and Dodge" },
    { "level": "Basic", "call": "Head Ladies Chain" },
    { "level": "Basic", "call": "Promenade 3/4" },
    { "level": "Basic", "call": "BOYS Walk GIRLS Dodge" },
    { "level": "Basic", "call": "GIRLS Walk BOYS Dodge" },
    { "level": "Basic", "call": "Lead Right|Veer Left" },
    { "level": "Basic", "call": "Slide Thru" },
    { "level": "Basic", "call": "Pass Thru|Wheel Around" },
    { "level": "Basic", "call": "Pass Thru|Separate around 1 to a Line" },
    { "level": "Basic", "call": "Pass Thru|Separate around 2 to a Line" },
    { "level": "Basic", "call": "Left Square Thru 4" },
    { "level": "Basic", "call": "Left Touch 1/4|GIRLS Run (Left)" },
    { "level": "Basic", "call": "Square Thru 2" },
    { "level": "Basic", "call": "All 4 Ladies Chain" },
    { "level": "Basic", "call": "Square Thru 3|Cloverleaf" },
    { "level": "Basic", "call": "Touch 1/4|BOYS Run" },
    { "level": "Basic", "call": "Box the Gnat|Slide Thru" },
    { "level": "Basic", "call": "Lead Left" },
    { "level": "Basic", "call": "Lead Left|Veer Right" },
    { "level": "Basic", "call": "Head Ladies Chain|Square Thru 2" },
    { "level": "Basic", "call": "Right and Left Thru|Pass the Ocean" },
    { "level": "Basic", "call": "Separate and Star Thru" },
    { "level": "Basic", "call": "1/2 Sashay|Slide Thru" },
    { "level": "Basic", "call": "Spin the Top|Extend" },
    { "level": "Basic", "call": "Sides Face Grand Square (6 steps to a line)" },
    { "level": "Basic", "call": "U-turn Back|Cloverleaf|Double Pass Thru|Cast Off 3/4" },
    { "level": "Basic", "call": "Box the Gnat|Touch 1/4|Walk and Dodge" },
    { "level": "Basic", "call": "Right and Left Thru|Flutter Wheel|Sweep 1/4" },
    { "level": "Basic", "call": "Promenade 1/4" },
    { "level": "Basic", "call": "Dosado to a Wave" },
    { "level": "Basic", "call": "Lead Right" },
    { "level": "Basic", "call": "Lead Right|Circle to a Line" },
    { "level": "Basic", "call": "Pass the Ocean" },
    { "level": "Basic", "call": "Square Thru 3" },
    { "level": "Basic", "call": "Square Thru 4" },
    { "level": "Basic", "call": "Heads Square Thru 4|Sides 1/2 Sashay" },
    { "level": "Basic", "call": "AL in the Alamo Style" },
    { "level": "Basic", "call": "AL like an Allemande Thar" },
    { "level": "Basic", "call": "AL|All 8 Spin the Top" },
    { "level": "MS",    "call": "Swing Thru|Spin the Top" },
    { "level": "MS",    "call": "Pass the Ocean|Centers Trade" },
    { "level": "MS",    "call": "Slide Thru|Partner Trade" },
    { "level": "MS",    "call": "Lead Right|Right and Left Thru" },
    { "level": "MS",    "call": "Spin the Top" },
    { "level": "MS",    "call": "Walk Around Your Corner|Dopaso" },
    { "level": "Plus",  "call": "Touch 1/4|Spread" },
    { "level": "Plus",  "call": "Star Thru|Spread" },
    { "level": "Plus",  "call": "Right and Left Thru|Dixie Style|Trade the Wave" },
    { "level": "Plus",  "call": "Teacup Chain" },
    { "level": "Plus",  "call": "Fan the Top" },
    { "level": "Plus",  "call": "Pass Thru|Chase Right" },
    { "level": "Plus",  "call": "Pass Thru|Left Chase" },
    { "level": "A1",    "call": "Wheel Thru" },
    { "level": "A1",    "call": "Left Wheel Thru" }
  ],

  "focusCalls": [
    { "level": "Plus",  "call": "Acey Deucey", "done": false  },
    { "level": "Plus",  "call": "Chase Right", "done": false  },
    { "level": "Plus",  "call": "Coordinate", "done": false  },
    { "level": "Plus",  "call": "Crossfire", "done": false  },
    { "level": "Plus",  "call": "Cut the Diamond", "done": false  },
    { "level": "Plus",  "call": "Dixie Grand", "done": false  },
    { "level": "MS",    "call": "Eight Chain 4", "done": false  },
    { "level": "Plus",  "call": "Explode and", "done": false  },
    { "level": "Plus",  "call": "Explode the Wave", "done": false  },
    { "level": "Plus",  "call": "Fan the Top", "done": false  },
    { "level": "Plus",  "call": "Flip the Diamond", "done": false  },
    { "level": "Plus",  "call": "Follow Your Neighbor", "done": false  },
    { "level": "Plus",  "call": "Grand Swing Thru", "done": false  },
    { "level": "MS",    "call": "Half Tag", "done": false },
    { "level": "Plus",  "call": "Left Chase", "done": false  },
    { "level": "MS",    "call": "Left Half Tag", "done": false  },
    { "level": "MS",    "call": "Left Square Thru", "done": false  },
    { "level": "Plus",  "call": "Linear Cycle", "done": false  },
    { "level": "Plus",  "call": "Load the Boat", "done": false  },
    { "level": "Plus",  "call": "Peel Off", "done": false  },
    { "level": "Plus",  "call": "Peel The Top", "done": false  },
    { "level": "Plus",  "call": "Ping Pong Circulate", "done": false  },
    { "level": "Plus",  "call": "Relay The Deucey", "done": false  },
    { "level": "MS",    "call": "Right & Left Thru (+1/4)", "done": false  },
    { "level": "Plus",  "call": "Single Circle To A Wave", "done": false  },
    { "level": "Plus",  "call": "Spin Chain & Xchg Gears", "done": false  },
    { "level": "Plus",  "call": "Spin Chain The Gears", "done": false  },
    { "level": "MS",    "call": "Spin Chain Thru", "done": false  },
    { "level": "MS",    "call": "Split Circulate 1-1/2", "done": false  },
    { "level": "MS",    "call": "Swing Thru 1-1/2", "done": false  },
    { "level": "MS",    "call": "Tag the Line", "done": false  },
    { "level": "Plus",  "call": "Teacup Chain", "done": false  },
    { "level": "Plus",  "call": "Track 2", "done": false  },
    { "level": "Plus",  "call": "Triple Scoot", "done": false  },
    { "level": "Plus",  "call": "1/4 Tag the Line", "done": false  },
    { "level": "MS",    "call": "3/4 Tag the Line", "done": false  }
  ],

  "resolves": [
    { "level": "MS",   "from": "1P2P", "calls": "Flutter Wheel|Sweep 1/4|Pass Thru|AL" },
    { "level": "MS",   "from": "1P2P", "calls": "Pass the Ocean|GIRLS Trade|GIRLS Run|BOYS Trade|BOYS Fold|RLG" },
    { "level": "MS",   "from": "1P2P", "calls": "Pass the Ocean|Split Circulate 2X|RLG" },
    { "level": "MS",   "from": "1P2P", "calls": "Pass Thru|1/2 Tag|Swing Thru|Split Circulate|BOYS Run|AL" },
    { "level": "MS",   "from": "1P2P", "calls": "Pass Thru|Tag the Line|Cloverleaf|Zoom|CENTERS AL|ALL RLG" },
    { "level": "MS",   "from": "1P2P", "calls": "Pass Thru|Wheel and Deal|Centers Pass Thru|Pass the Ocean|Spin the Top|RLG" },
    { "level": "MS",   "from": "1P2P", "calls": "Pass Thru|Wheel and Deal|Centers Slide Thru|Touch 1/4|Walk and Dodge|AL" },
    { "level": "MS",   "from": "1P2P", "calls": "Right and Left Thru and 1/4 more|Ferris Wheel|Centers Swing Thru 2X|Ping-Pong Circulate|Centers Swing Thru|Centers Turn Thru|AL" },
    { "level": "MS",   "from": "1P2P", "calls": "Right and Left Thru|Dixie Style to a Wave|BOYS Scootback|GIRLS Circulate|AL" },
    { "level": "MS",   "from": "1P2P", "calls": "Right and Left Thru|Spin the Top|Swing Thru|BOYS Run|PROMENADE" },
    { "level": "MS",   "from": "1P2P", "calls": "Slide Thru|Swing Thru 2X|All 8 Circulate|8 Chain 3|AL" },
    { "level": "MS",   "from": "1P2P", "calls": "Square Thru 4|Trade By|8 Chain 3|AL" },
    { "level": "MS",   "from": "1P2P", "calls": "Touch 1/4|All 8 Circulate 3X|BOYS Run|AL" },
    { "level": "MS",   "from": "CB",  "calls": "Relay the Deucey|Recycle|Veer Left|GIRLS Trade|Wheel and Deal|AL" },
    { "level": "MS",   "from": "CB",  "calls": "Right and Left Thru|Dive Thru|Square Thru 3|AL" },
    { "level": "MS",   "from": "CB",  "calls": "Right and Left Thru|Swing Thru|RLG" },
    { "level": "MS",   "from": "CB",  "calls": "Slide Thru|Pass the Ocean|GIRLS Trade|BOYS Cross Fold|AL" },
    { "level": "MS",   "from": "CB",  "calls": "Spin Chain Thru|GIRLS Circulate 2X|Turn Thru|AL" },
    { "level": "MS",   "from": "CB",  "calls": "Star Thru|Pass Thru|Bend the Line|Star Thru|AL" },
    { "level": "MS",   "from": "CB",  "calls": "Star Thru|Right and Left Thru|Touch 1/4|All 8 Circulate 2X|GIRLS U-turn Back|AL" },
    { "level": "MS",   "from": "CB",  "calls": "Swing Thru/BOYS Run|Couples Circulate|Bend the Line|Right and Left Thru/Dixie Style|GIRLS Circulate 2X|BOYS Trade 2X|AL" },
    { "level": "MS",   "from": "CB",  "calls": "Swing Thru|BOYS Run|Bend the Line|Pass the Ocean|GIRLS Cross fold|AL" },
    { "level": "MS",   "from": "CB",  "calls": "Swing Thru|BOYS Run|Bend the Line|Pass Thru|Wheel and Deal|AL" },
    { "level": "MS",   "from": "CB",  "calls": "Swing Thru|BOYS Run|Bend the Line|Pass Thru|Wheel and Deal|Centers Pass Thru|AL" },
    { "level": "Plus", "from": "CB",  "calls": "Swing Thru|BOYS Run|Crossfire|Coordinate|BOYS Circulate|Wheel and Deal|AL" },
    { "level": "MS",   "from": "CB",  "calls": "Swing Thru|BOYS Run|Tag the Line, Face RIGHT|Wheel and Deal|Touch 1/4 & Roll|Change Hands & AL" },
    { "level": "MS",   "from": "CB",  "calls": "Swing Thru|Scootback (BG)|Recycle|AL" },
    { "level": "MS",   "from": "CB",  "calls": "Swing Thru|Spin the Top|Right and Left Thru|2 Ladies Chain|Dixie Style to AL" },
    { "level": "MS",   "from": "CB",  "calls": "Touch 1/4|Follow Your Neighbor|AL" },
    { "level": "MS",   "from": "CWave",  "calls": "All 8 Circulate 1-1/2|Slide Thru|AL" },
    { "level": "Plus", "from": "1P2P", "calls": "Box the Gnat|Load the Boat|RLG" },
    { "level": "Plus", "from": "1P2P", "calls": "Pass the Ocean|Explode the Wave|Partner Trade|AL" },
    { "level": "Plus", "from": "1P2P", "calls": "Pass the Ocean|GIRLS Run|BOYS Hinge|Diamond Circulate|Flip the Diamond|RLG" },
    { "level": "Plus", "from": "1P2P", "calls": "Pass the Ocean|Swing Thru|BOYS Run/GIRLS Trade|Ferris Wheel|Double Pass Thru/Track 2|Swing Thru/Turn Thru|AL" },
    { "level": "Plus", "from": "1P2P", "calls": "Pass Thru|Chase Right|Partner Trade & Roll|RLG" },
    { "level": "Plus", "from": "1P2P", "calls": "Pass Thru|Tag the Line Face IN|Touch 1/4|BOYS Run|Pass Thru|AL" },
    { "level": "Plus", "from": "1P2P", "calls": "Right and Left Thru|Pass Thru|Partner Trade & Roll|Pass Thru/Trade By|Pass Thru/Trade By|RLG" },
    { "level": "Plus", "from": "1P2P", "calls": "Right and Left Thru|Slide Thru 2X|Roll (once)|RLG" },
    { "level": "Plus", "from": "1P2P", "calls": "Right and Left Thru|Star Thru|Single Circle to RLG" },
    { "level": "Plus", "from": "1P2P", "calls": "Touch 1/4|Coordinate|Bend the Line|Pass the Ocean|Trade the Wave|AL" },
    { "level": "Plus", "from": "1P2P", "calls": "Touch 1/4|Triple Scoot|BOYS Run|Square Thru 3|AL" },
    { "level": "MS", "from": "1P2P", "calls": "CENTERS Square Thru 4|ENDS Allemande Left|Everybody RLG" },
    { "level": "MS", "from": "1P2P", "calls": "Pass the Ocean|Hinge|CENTERS Trade|CENTERS Run|Half Tag|RLG" },
    { "level": "MS", "from": "1P2P", "calls": "Ladies Chain|Pass the Ocean|Swing Thru|RLG" },
    { "level": "Plus", "from": "1P2P", "calls": "Pass Thru|Bend The Line|Load The Boat|Wrong Way Weave the Ring" },
    { "level": "MS", "from": "1P2P", "calls": "Pass Thru|Wheel and Deal|Double Pass Thru|First Left, Next Left|Promenade Home" },
    { "level": "MS", "from": "1P2P", "calls": "Right and Left Thru|Slide Thru|Box the Gnat|RLG" },
    { "level": "MS", "from": "1P2P", "calls": "Slide Thru|Touch 1/4|Split Circulate TWICE|Face Right|RLG" },
    { "level": "MS", "from": "1P2P", "calls": "MEN Extend|Swing Thru|Cast Off 3/4|LADIES Face Right|Circulate TWICE|AL" },
    { "level": "Plus", "from": "1P2P", "calls": "Grand Swing Thru|BOYS Run|Bend the Line|AL" },
    { "level": "Basic", "from": "1P2P", "calls": "Step to a Wave|Swing Thru|VERY CENTER GIRLS Trade|BOYS Run|Bend the Line|AL" },
    { "level": "Basic", "from": "1P2P", "calls": "Left Square Thru 4" },
    { "level": "Basic", "from": "1P2P", "calls": "Square Thru 3|BOYS Fold (face a girl)|Star Thru|Promenade Home" },
    { "level": "Plus", "from": "1P2P", "calls": "Slide Thru|Touch 1/4|GIRLS Run|Load the Boat|RLG" },
    { "level": "MS", "from": "1P2P", "calls": "Slide Thru|Touch 1/4|GIRLS Run|Pass the Ocean|RLG" },
    { "level": "MS", "from": "1P2P", "calls": "Pass the Ocean|Split Circulate TWICE|RLG" },
    { "level": "MS", "from": "1P2P", "calls": "Square Thru 3|Partner Trade 1 1/2|RLG" },
    { "level": "MS", "from": "1P2P", "calls": "Right and Left Thru|1/2 Sashay|Pass the Ocean|RLG" },
    { "level": "MS", "from": "1P2P", "calls": "Touch 1/4|Walk and Dodge|Trade By|Right and Left Thru|Swing Thru|Square Thru|On the 3rd Hand RLG" },
    { "level": "MS", "from": "1P2P", "calls": "Pass Thru|Bend the Line|Tag the Line|LEADERS AL|Everybody RLG" },
    { "level": "MS", "from": "1P2P", "calls": "Pass the Ocean|Scoot Back|RLG" },
    { "level": "MS", "from": "1P2P", "calls": "Slide Thru|Square Thru 3|AL" },
    { "level": "Basic", "from": "1P2P", "calls": "Pass Thru|Wheel and Deal|CENTERS Sweep 1/4|AL" },
    { "level": "MS", "from": "1P2P", "calls": "Spin the Top|BOYS Cross Fold|RLG" },
    { "level": "Plus", "from": "1P2P", "calls": "Dixie Style to a Wave|Swing Thru (BOYS start)|Trade the Wave|RLG" },
    { "level": "MS", "from": "1P2P", "calls": "Right and Left Thru|Pass Thru|Tag the Line Face IN|Slide Thru|AL" },
    { "level": "MS", "from": "1P2P", "calls": "Pass Thru|Wheel and Deal|CENTERS Swing Thru and CO 3/4|AL" },
    { "level": "MS", "from": "1P2P", "calls": "ENDS Slide Thru|CENTERS Pass the Ocean|Swing Thru|Extend|Recycle|AL" },
    { "level": "Plus", "from": "1P2P", "calls": "Right and Left Thru|Pass the Ocean|Spin Chain Thru|GIRLS circulate|RLG" },
    { "level": "MS", "from": "1P2P", "calls": "Box the Gnat|Slide Thru|AL" },
    { "level": "MS", "from": "1P2P", "calls": "Flutter Wheel|Sweep 1/4|Split the Outsides|AL" },
    { "level": "MS", "from": "1P2P", "calls": "1/2 Sashay|Square Thru|On the 3rd hand, Slide Thru|AL" },
    { "level": "MS", "from": "1P2P", "calls": "Spin the Top|BOYS Trade|RLG" },
    { "level": "MS", "from": "1P2P", "calls": "Right and Left Thru|Dixie Style to a Wave|BOYS Cross Run|BOYS Run|Promenade Home" },
    { "level": "MS", "from": "1P2P", "calls": "Pass Thru|Wheel and Deal|CENTERS Pass Thru|Swing Thru|Turn Thru|AL" },
    { "level": "MS", "from": "1P2P", "calls": "Wheel Around 1 1/2|Promenade Home" },
    { "level": "Plus", "from": "CB",  "calls": "Pass to the Center|Centers Swing Thru 2X|Ping-Pong Circulate|Centers Trade the Wave|Step Thru|AL" },
    { "level": "Plus", "from": "CB",  "calls": "Right and Left Thru|Dive Thru|Zoom|Dixie Grand|AL" },
    { "level": "Plus", "from": "CB",  "calls": "Right and Left Thru|Star Thru|Load the Boat|AL" },
    { "level": "Plus", "from": "CB",  "calls": "Slide Thru|Pass the Ocean|Trade the Wave|AL" },
    { "level": "Plus", "from": "CB",  "calls": "Spin Chain the Gears|Hinge|Follow Your Neighbor|AL" },
    { "level": "Plus", "from": "CB",  "calls": "Star Thru|Right and Left Thru|Pass Thru|Chase Right|BOYS Run|Slide Thru|AL" },
    { "level": "Plus", "from": "CB",  "calls": "Swing Thru 2X|Trade the Wave|AL" },
    { "level": "Plus", "from": "CB",  "calls": "Swing Thru|GIRLS Fold|Peel the Top|Right and Left Thru|Star Thru|Dive Thru/Square Thru 3|AL" },
    { "level": "Plus", "from": "CB",  "calls": "Swing Thru|Spin the Top|Hinge|Triple Scoot|BOYS Run|AL" },
    { "level": "Plus", "from": "CB",  "calls": "Touch 1/4|Follow Your Neighbor & Spread|All 8 Trade|All 8 Fold|AL" },
    { "level": "Plus", "from": "CB",  "calls": "Touch 1/4|Follow Your Neighbor & Spread|Explode the Wave|Partner Trade|Slide Thru|AL" },
    { "level": "Plus", "from": "CL",  "calls": "Right and Left Thru|Load the Boat|AL" },

    { "level": "Basic",    "from": "1P2P", "calls": "AL" },
    { "level": "Basic",    "from": "1P2P", "calls": "Box The Gnat|Pass The Ocean|Right & Left Grand" },
    { "level": "Basic",    "from": "1P2P", "calls": "Flutter Wheel|Lead Right|Allemande Left" },
    { "level": "Basic",    "from": "1P2P", "calls": "Left Square Thru|AL" },
    { "level": "Basic",    "from": "1P2P", "calls": "Left Touch 3/4|Single File Promenade Home" },
    { "level": "Basic",    "from": "1P2P", "calls": "Pass The Ocean|Split Circulate Twice|RLG" },
    { "level": "Basic",    "from": "1P2P", "calls": "Pass Thru|Couples Trade|Allemande Left" },
    { "level": "Basic",    "from": "1P2P", "calls": "Pass Thru|Wheel And Deal, Centers Sweep 1/4|Home" },
    { "level": "Basic",    "from": "1P2P", "calls": "Right & Left Thru|Half Sashay|Pass The Ocean|RLG" },
    { "level": "Basic",    "from": "1P2P", "calls": "Right & Left Thru|Star Thru|Box The Gnat|RLG" },
    { "level": "Basic",    "from": "1P2P", "calls": "Square Thru 3|Bend The Line|Allemande Left" },
    { "level": "Basic",    "from": "1P2P", "calls": "Square Thru 4|U-Turn Back|Right & Left Grand" },
    { "level": "Basic",    "from": "1P2P", "calls": "Star Thru|Square Thru 3|Allemande Left" },
    { "level": "Basic",    "from": "1P2P", "calls": "Star Thru|Trade|Allemande Left" },
    { "level": "Basic",    "from": "1P2P", "calls": "Touch 1/4|Circulate|Partner Trade|Girls U-Turn Back|AL" },
    { "level": "Basic",    "from": "1P2P", "calls": "Touch 1/4|Column Circulate|Boys Run|AL" },
    { "level": "Basic",    "from": "1P2P", "calls": "Touch 1/4|Girls Run|RLG" },

    { "level": "MS",    "from": "1P2P", "calls": "Cast Off 3/4|AL" },
    { "level": "MS",    "from": "1P2P", "calls": "Flutter Wheel|Spin The Top|Right & Left Grand" },
    { "level": "MS",    "from": "1P2P", "calls": "Hinge|RLG" },
    { "level": "MS",    "from": "1P2P", "calls": "Left Square Thru On 4|Box The Gnat|RLG" },
    { "level": "MS",    "from": "1P2P", "calls": "Pass The Ocean|Recycle Twice|RLG" },
    { "level": "MS",    "from": "1P2P", "calls": "Pass The Ocean|Swing Thru|Recycle|RLG" },
    { "level": "MS",    "from": "1P2P", "calls": "Pass Thru|Tag The Line In|Turn Thru|Ends Fold|RLG" },
    { "level": "MS",    "from": "1P2P", "calls": "Recycle|Center Wave Spin The Top|RLG" },
    { "level": "MS",    "from": "1P2P", "calls": "Right & Left Thru|Pass The Ocean|Spin Chain Thru, Ends Circulate Once|RLG" },
    { "level": "MS",    "from": "1P2P", "calls": "Right & Left Thru|Pass The Ocean|Spin Chain Thru, Girls Circulate|RLG" },
    { "level": "MS",    "from": "1P2P", "calls": "Right And Left Thru|Pass The Ocean|Scoot Back|RLG" },
    { "level": "MS",    "from": "1P2P", "calls": "Slide Thru|Square Thru 3|Allemande Left" },
    { "level": "MS",    "from": "1P2P", "calls": "Square Thru|Trade By|Turn Thru|Trade By|RLG" },

    { "level": "Plus",    "from": "1P2P", "calls": "Box The Gnat|Load The Boat|RLG" },
    { "level": "Plus",    "from": "1P2P", "calls": "Cast Off 3/4 New Centers Roll|AL" },
    { "level": "Plus",    "from": "1P2P", "calls": "Centers 3/4 Load The Boat|AL" },
    { "level": "Plus",    "from": "1P2P", "calls": "Fan The Top|Swing Thru|Right & Left Grand" },
    { "level": "Plus",    "from": "1P2P", "calls": "Load The Boat|Square Thru 3|AL" },
    { "level": "Plus",    "from": "1P2P", "calls": "Pass The Ocean|Boys Circulate|Trade The Wave|8 Circulate|AL" },
    { "level": "Plus",    "from": "1P2P", "calls": "Pass The Ocean|Centers Trade & Run|1/2 Tag Trade & Roll|RLG" },
    { "level": "Plus",    "from": "1P2P", "calls": "Pass The Ocean|Girls Hinge & U-Turn Back|Diamond Circulate Twice|Flip The Diamond|RLG" },
    { "level": "Plus",    "from": "1P2P", "calls": "Pass The Ocean|Linear Cycle & Roll|Girls Peel Off|RLG" },
    { "level": "Plus",    "from": "1P2P", "calls": "Pass Thru|Bend The Line & Roll|Double Pass Thru|Leads U-Turn Back|RLG" },
    { "level": "Plus",    "from": "1P2P", "calls": "Pass Thru|Bend The Line Twice|Slide Thru Twice And Roll|RLG" },
    { "level": "Plus",    "from": "1P2P", "calls": "Pass Thru|Chase Right|Follow Your Neighbor & Spread|RLG" },
    { "level": "Plus",    "from": "1P2P", "calls": "Pass Thru|Chase Right|Scoot Back|Single Hinge|RLG" },
    { "level": "Plus",    "from": "1P2P", "calls": "Pass Thru|Chase Right|Trade & Roll|RLG" },
    { "level": "Plus",    "from": "1P2P", "calls": "Pass Thru|Explode And Load The Boat|RLG" },
    { "level": "Plus",    "from": "1P2P", "calls": "Pass Thru|Left Chase|Follow Your Neighbor|RLG" },
    { "level": "Plus",    "from": "1P2P", "calls": "Pass Thru|Partner Trade & Roll|Square Thru On 3|RLG" },
    { "level": "Plus",    "from": "1P2P", "calls": "Pass Thru|Tag The Line|Peel Off|AL" },
    { "level": "Plus",    "from": "1P2P", "calls": "Right & Left Thru, Rollaway|Load The Boat|RLG" },
    { "level": "Plus",    "from": "1P2P", "calls": "Right & Left Thru|Dixie Style To An Ocean Wave|Acey Deucey|AL" },
    { "level": "Plus",    "from": "1P2P", "calls": "Right & Left Thru|Dixie Style To An Ocean Wave|Left Swing Thru|Trade The Wave|RLG" },
    { "level": "Plus",    "from": "1P2P", "calls": "Right & Left Thru|Flutter Wheel|Centers Fan The Top, Others Box The Gnat|RLG" },
    { "level": "Plus",    "from": "1P2P", "calls": "Right & Left Thru|Load The Boat|Single Circle To A Wave|RLG" },
    { "level": "Plus",    "from": "1P2P", "calls": "Right & Left Thru|Pass The Ocean|Relay The Deucey|Boys Run|Promenade Home" },
    { "level": "Plus",    "from": "1P2P", "calls": "Right & Left Thru|Slide Thru Twice & Roll|RLG" },
    { "level": "Plus",    "from": "1P2P", "calls": "Right & Left Thru|Touch 1/4|Peel Off|Promenade Home" },
    { "level": "Plus",    "from": "1P2P", "calls": "Square Thru 3/4|Partner Trade & Roll|RLG" },

    { "level": "A1",    "from": "1P2P", "calls": "1/2 Square Thru|Left Roll To A Wave|Mix|RLG"  },
    { "level": "A1",    "from": "1P2P", "calls": "1/4 In|RLG"  },
    { "level": "A1",    "from": "1P2P", "calls": "1/4 Out|AL"  },
    { "level": "A1",    "from": "1P2P", "calls": "As Couples Beau Walk Belle Dodge|Wrong Way Promenade Home"  },
    { "level": "A1",    "from": "1P2P", "calls": "As Couples Belles Walk Beaus Dodge|Promenade Home"  },
    { "level": "A1",    "from": "1P2P", "calls": "Cross Trail Thru|Bend The Line|Cross Trail Thru|Ends Fold|RLG"  },
    { "level": "A1",    "from": "1P2P", "calls": "Cross Trail Thru|Ends Fold|Square Thru 3/4|AL"  },
    { "level": "A1",    "from": "1P2P", "calls": "Double Star Thru|Explode Double Star Thru & Roll|RLG"  },
    { "level": "A1",    "from": "1P2P", "calls": "Grand Swing Thru|Brace Thru|Star Thru|AL"  },
    { "level": "A1",    "from": "1P2P", "calls": "Pass Thru|As Couples Beaus Run|Each Side Beaus Run|RLG"  },
    { "level": "A1",    "from": "1P2P", "calls": "Pass Thru|Chase Right|Boys Run|Reverse The Flutter|Left Wheel Thru, AL"  },
    { "level": "A1",    "from": "1P2P", "calls": "Pass Thru|Right Roll To A Wave|Lockit|RLG"  },
    { "level": "A1",    "from": "1P2P", "calls": "Pass Thru|Tag The Line In|Pass The Sea|Mix|RLG"  },
    { "level": "A1",    "from": "1P2P", "calls": "Pass Thru|Tag The Line Right|Couples Circulate|1/4 Out|AL"  },
    { "level": "A1",    "from": "1P2P", "calls": "Pass Thru|Wheel & Deal|Centers Square Thru On 4, Left Square Chain Thru|AL"  },
    { "level": "A1",    "from": "1P2P", "calls": "Pass Thru|Wheel & Deal|Centers Swap Around|AL"  },
    { "level": "A1",    "from": "1P2P", "calls": "Right & Left Thru|Cross Trail Thru To The Corner|AL"  },
    { "level": "A1",    "from": "1P2P", "calls": "Right & Left Thru|Double Star Thru & Roll|RLG"  },
    { "level": "A1",    "from": "1P2P", "calls": "Single Circle To A Wave|Lockit|RLG"  },
    { "level": "A1",    "from": "1P2P", "calls": "Square Chain Thru|Centers Swing Thru, Others Trade & Roll|RLG"  },
    { "level": "A1",    "from": "1P2P", "calls": "Square Thru 3|Partner Hinge|Scoot Back|RLG"  },
    { "level": "A1",    "from": "1P2P", "calls": "Square Thru|Right Roll To A Wave|RLG"  },
    { "level": "A1",    "from": "1P2P", "calls": "Star Thru|Pass Thru|Left Roll To A Wave|Trade The Wave|RLG"  },
    { "level": "A1",    "from": "1P2P", "calls": "Touch 1/4 & Cross|Centers Flutter Wheel|RLG"  },
    { "level": "A1",    "from": "1P2P", "calls": "Touch 1/4|Boys Run|Right Roll To A Wave|RLG"  },
    { "level": "A1",    "from": "1P2P", "calls": "Touch 1/4|Circulate|Scoot & Dodge|RLG"  },
    { "level": "A2",    "from": "1P2P", "calls": "Boys Walk, Girls Dodge|Scoot & Weave|RLG" },
    { "level": "A2",    "from": "1P2P", "calls": "Pass The Ocean|Girls Run|Mini Busy|Chain Reaction|RLG" },
    { "level": "A2",    "from": "1P2P", "calls": "Pass The Ocean|Motivate, Star 3/4|8 Circulate|RLG" },
    { "level": "A2",    "from": "1P2P", "calls": "Pass The Ocean|Out Roll Circulate Twice|RLG" },
    { "level": "A2",    "from": "1P2P", "calls": "Pass The Ocean|Scoot Back|Split Counter Rotate 1/4|Split Transfer|RLG" },
    { "level": "A2",    "from": "1P2P", "calls": "Pass The Ocean|Slip, Swing, Slip|RLG" },
    { "level": "A2",    "from": "1P2P", "calls": "Pass The Ocean|Split Circulate|Single Wheel|Pass & Roll|RLG" },
    { "level": "A2",    "from": "1P2P", "calls": "Pass The Ocean|Split Transfer Twice|RLG" },
    { "level": "A2",    "from": "1P2P", "calls": "Pass The Sea Swing & Mix|RLG" },
    { "level": "A2",    "from": "1P2P", "calls": "Pass The Sea|Left 1/4 Thru|Scoot Chain Thru|AL" },
    { "level": "A2",    "from": "1P2P", "calls": "Pass The Sea|Slip & Swing|Slip & Slide|RLG" },
    { "level": "A2",    "from": "1P2P", "calls": "Pass Thru|3/4 Tag The Line|Spin The Windmill Out|Cycle & Wheel|Dixie Grand, AL" },
    { "level": "A2",    "from": "1P2P", "calls": "Pass Thru|Chase Right|Scoot Back|Extend The Tag|Spin The Windmill Left, AL" },
    { "level": "A2",    "from": "1P2P", "calls": "Pass Thru|Single Wheel|On The Double Track Dixie Style To A Wave|Acey Deucey|AL" },
    { "level": "A2",    "from": "1P2P", "calls": "Right & Left Thru|Dixie Style To An Ocean Wave|Slip, Slide, Swing|RLG" },
    { "level": "A2",    "from": "1P2P", "calls": "Right & Left Thru|Pass The Ocean|In Roll Circulate Twice|RLG" },
    { "level": "A2",    "from": "1P2P", "calls": "Touch 1/4|Split Transfer|3/4 Thru|RLG" },
    { "level": "A2",    "from": "1P2P", "calls": "Touch 1/4|Triple Scoot|Checkmate|Bend The Line & Roll|Right Roll To A Wave, RLG" },
    { "level": "A2",    "from": "1P2P", "calls": "Touch 1/4|Triple Scoot|Column Circulate|Grand Remake|Girls Run|RLG" },
    { "level": "A2",    "from": "1P2P", "calls": "Touch 1/4|Triple Scoot|Split Counter Rotate 1/4|3/4 Thru|RLG" },

    { "level": "Basic",    "from": "CB", "calls": "1/2 Square Thru|U-Turn Back|1/2 Square Thru|RLG" },
    { "level": "Basic",    "from": "CB", "calls": "3/4 Dosado|AL" },
    { "level": "Basic",    "from": "CB", "calls": "Allemande Left" },
    { "level": "Basic",    "from": "CB", "calls": "Box The Gnat|Pull By|Dopaso To Roll Promenade Home" },
    { "level": "Basic",    "from": "CB", "calls": "Left Touch|AL" },
    { "level": "Basic",    "from": "CB", "calls": "Square Thru|U-Turn Back|Square Thru|RLG" },
    { "level": "Basic",    "from": "CB", "calls": "Swing Thru 1 & 1/2|Boys Cross Run|AL" },
    { "level": "Basic",    "from": "CB", "calls": "Touch 1/2|Extend|RLG" },
    { "level": "MS",    "from": "CB", "calls": "Centers Face IN And Backaway|Home" },
    { "level": "MS",    "from": "CB", "calls": "Left Turn Thru|RLG" },
    { "level": "MS",    "from": "CB", "calls": "Right & Left Thru|Pass To The Center|Centers Slide Thru 3 Times|Home" },
    { "level": "MS",    "from": "CB", "calls": "Right & Left Thru|Touch 1/4|Scoot Back 1 & 1/2|Wheel & Deal|AL" },
    { "level": "MS",    "from": "CB", "calls": "Slide Thru|Reverse Flutter Wheel, Sweep 1/4|AL" },
    { "level": "MS",    "from": "CB", "calls": "Spin Chain Thru, Ends Circulate 2|RLG" },
    { "level": "MS",    "from": "CB", "calls": "Spin Chain Thru|Girls Circulate Twice|RLG" },
    { "level": "MS",    "from": "CB", "calls": "Square Thru|Ends Fold|Pass Thru|RLG" },
    { "level": "MS",    "from": "CB", "calls": "Touch 1/4|Scoot Back|Boys Run|Reverse The Flutter, Sweep 1/4|AL" },
    { "level": "Plus",    "from": "CB", "calls": "Dive Thru|Dixie Grand|AL" },
    { "level": "Plus",    "from": "CB", "calls": "Left Relay The Deucey|AL" },
    { "level": "Plus",    "from": "CB", "calls": "Left Spin Chain The Gears|AL" },
    { "level": "Plus",    "from": "CB", "calls": "Pass The Ocean|Swing Thru|Spin The Top & Spread|AL" },
    { "level": "Plus",    "from": "CB", "calls": "Pass Thru|Chase Right|Boys Run|AL" },
    { "level": "Plus",    "from": "CB", "calls": "Pass Thru|Chase Right|Column Circulate|Girls Run|RLG" },
    { "level": "Plus",    "from": "CB", "calls": "Pass Thru|Dixie Grand|AL" },
    { "level": "Plus",    "from": "CB", "calls": "Pass To The Center|Dixie Grand|AL" },
    { "level": "Plus",    "from": "CB", "calls": "Relay The Deucey & Spread|AL" },
    { "level": "Plus",    "from": "CB", "calls": "Right & Left Thru|Half Sashay|Star Thru & Roll|AL" },
    { "level": "Plus",    "from": "CB", "calls": "Right & Left Thru|Spin Chain & Exchange The Gears|Left Swing Thru|RLG" },
    { "level": "Plus",    "from": "CB", "calls": "Single Circle To A Wave|Extend|RLG" },
    { "level": "Plus",    "from": "CB", "calls": "Slide Thru|Pass The Ocean|Trade The Wave|AL" },
    { "level": "Plus",    "from": "CB", "calls": "Slide Thru|Right & Left Thru|Load The Boat|AL" },
    { "level": "Plus",    "from": "CB", "calls": "Spin Chain The Gears|Scoot Back|1/2 Circulate|RLG" },
    { "level": "Plus",    "from": "CB", "calls": "Star Thru|Pass The Ocean|Explode|Load The Boat|AL" },
    { "level": "Plus",    "from": "CB", "calls": "Star Thru|Pass The Ocean|Trade The Wave|AL" },
    { "level": "Plus",    "from": "CB", "calls": "Star Thru|Pass Thru|Left Chase|Single Hinge|AL" },
    { "level": "Plus",    "from": "CB", "calls": "Swing Thru Twice|Explode Load The Boat|AL" },
    { "level": "Plus",    "from": "CB", "calls": "Swing Thru|Acey Deucey|RLG" },
    { "level": "Plus",    "from": "CB", "calls": "Swing Thru|Boys Trade|Trade The Wave|Swing Thru 1 & 1/2|AL" },
    { "level": "Plus",    "from": "CB", "calls": "Swing Thru|Spin The Top|Explode|AL" },
    { "level": "Plus",    "from": "CB", "calls": "Swing Thru|Spin The Top|Grand Swing Thru|Explode RLG" },
    { "level": "Plus",    "from": "CB", "calls": "Swing Thru|Trade The Wave|Chain Down The Line|Square Thru On 4|AL" },
    { "level": "Plus",    "from": "CB", "calls": "Swing Thru|Trade The Wave|Swing Thru|AL" },
    { "level": "Plus",    "from": "CB", "calls": "Touch 1/4|Follow Your Neighbor|AL" },
    { "level": "Plus",    "from": "CB", "calls": "Touch 1/4|Scoot Back|Follow Your Neighbor & Spread|Extend|RLG" },
    { "level": "A1",    "from": "CB", "calls": "1/2 Square Thru|Explode The Line|Ends Bend & Roll|AL" },
    { "level": "A1",    "from": "CB", "calls": "Centers In|Single Hinge|Ends Bend|RLG" },
    { "level": "A1",    "from": "CB", "calls": "Centers Right Roll To A Wave|RLG" },
    { "level": "A1",    "from": "CB", "calls": "Double Star Thru & Roll|1/2 Square Thru|RLG" },
    { "level": "A1",    "from": "CB", "calls": "Pair Off & Roll|RLG" },
    { "level": "A1",    "from": "CB", "calls": "Pass The Ocean|Lock It|Mix|AL" },
    { "level": "A1",    "from": "CB", "calls": "Pass Thru|Centers Square Thru 3|Horseshoe Turn|AL" },
    { "level": "A1",    "from": "CB", "calls": "Pass Thru|Partner Trade|Partner Tag Twice|RLG" },
    { "level": "A1",    "from": "CB", "calls": "Relay The Deucey|Recycle & Roll |Left 1/4 Thru|AL" },
    { "level": "A1",    "from": "CB", "calls": "Right & Left Thru|1/2 Sashay|Pass Thru|Left Roll To A Wave|AL" },
    { "level": "A1",    "from": "CB", "calls": "Right & Left Thru|Cross Trail Thru|RLG" },
    { "level": "A1",    "from": "CB", "calls": "Right & Left Thru|Double Star Thru, Outsides Roll|RLG" },
    { "level": "A1",    "from": "CB", "calls": "Right & Left Thru|Double Star Thru|RLG" },
    { "level": "A1",    "from": "CB", "calls": "Right & Left Thru|Pass In Twice, Ends Roll|RLG" },
    { "level": "A1",    "from": "CB", "calls": "Right & Left Thru|Pass The Ocean|Pass The Sea|AL" },
    { "level": "A1",    "from": "CB", "calls": "Slide Thru|Turn Thru|Partner Tag|RLG" },
    { "level": "A1",    "from": "CB", "calls": "Spin Chain The Gears|Swing Thru|Cast A Shadow 3 Times|Promenade Home" },
    { "level": "A1",    "from": "CB", "calls": "Square Thru|Tag The Line|Partner Tag Twice|RLG" },
    { "level": "A1",    "from": "CB", "calls": "Star Thru|Right & Left Thru|Pass The Sea|AL" },
    { "level": "A1",    "from": "CB", "calls": "Swing Thru|Boys Run, Girls Walk & Dodge|Explode & Touch 1/4|Transfer The Column|RLG" },
    { "level": "A1",    "from": "CB", "calls": "Swing Thru|Girls U-Turn Back|All Cast A Shadow 3 Times|RLG" },
    { "level": "A1",    "from": "CB", "calls": "Touch 1/4|Scoot & Dodge|1/4 Out|RLG" },
    { "level": "A1",    "from": "CB", "calls": "Veer Left|Turn & Deal|Pass Thru|RLG" },
    { "level": "A2",    "from": "CB", "calls": "Half Sashay|Swing & Mix|AL" },
    { "level": "A2",    "from": "CB", "calls": "Left Pass & Roll Your Neighbor & Roll|RLG" },
    { "level": "A2",    "from": "CB", "calls": "Pass & Roll Your Neighbor|Hinge|AL" },
    { "level": "A2",    "from": "CB", "calls": "Pass The Ocean|Boys Run|Single Wheel Twice & Roll|AL" },
    { "level": "A2",    "from": "CB", "calls": "Relay The Deucey|In Roll Circulate Double|Extend|RLG" },
    { "level": "A2",    "from": "CB", "calls": "Slide Thru|Pass The Ocean|3/4 Thru|Scoot Chain Thru|RLG" },
    { "level": "A2",    "from": "CB", "calls": "Spin Chain & Exchange The Gears|Acey Deucey, Girls 1 & 1/2|All Diamond Chain Thru, Girls Circulate 1|AL" },
    { "level": "A2",    "from": "CB", "calls": "Square Thru|Wheel & Deal & Spread|Touch 1/4|Trail Off & Roll|Dixie Grand|AL" },
    { "level": "A2",    "from": "CB", "calls": "Star Thru|Right & Left Thru|Dixie Style To An Ocean Wave|Boys Remake, Girls Circulate|AL" },
    { "level": "A2",    "from": "CB", "calls": "Swing Thru|Acey Deucey|Switch The Wave|Turn & Deal|RLG" },
    { "level": "A2",    "from": "CB", "calls": "Swing Thru|Pass & Roll|Scoot Chain Thru|RLG" },
    { "level": "A2",    "from": "CB", "calls": "Swing Thru|Split Circulate|Slip, Slide, Hinge|AL" },
    { "level": "A2",    "from": "CB", "calls": "Touch 1/4|Split Counter Rotate & Cross|RLG" }

  ]

}
